pwhois
setup.py
pythonwhois/__init__.py
pythonwhois/net.py
pythonwhois/parse.py
pythonwhois/shared.py
pythonwhois.egg-info/PKG-INFO
pythonwhois.egg-info/SOURCES.txt
pythonwhois.egg-info/dependency_links.txt
pythonwhois.egg-info/requires.txt
pythonwhois.egg-info/top_level.txt