Metadata-Version: 1.1
Name: pythonwhois
Version: 2.1.0
Summary: Module for retrieving and parsing the WHOIS data for a domain. Supports most domains. No dependencies.
Home-page: http://cryto.net/pythonwhois
Author: Sven Slootweg
Author-email: pythonwhois@cryto.net
License: WTFPL
Platform: UNKNOWN
Provides: pythonwhois
